pipenv_package_requirements-0.2.dist-info/DESCRIPTION.rst
pipenv_package_requirements-0.2.dist-info/METADATA
pipenv_package_requirements-0.2.dist-info/RECORD
pipenv_package_requirements-0.2.dist-info/WHEEL
pipenv_package_requirements-0.2.dist-info/entry_points.txt
pipenv_package_requirements-0.2.dist-info/metadata.json
pipenv_package_requirements-0.2.dist-info/top_level.txt
pipenv_package_requirements-0.2.dist-info/zip-safe
pipenv_tools/__init__.py
pipenv_tools/command_line.py
